stream_downloader/__init__.py
stream_downloader/downloader.py
stream_downloader-0.1.1.dist-info/LICENSE
stream_downloader-0.1.1.dist-info/METADATA
stream_downloader-0.1.1.dist-info/WHEEL
stream_downloader-0.1.1.dist-info/top_level.txt
stream_downloader-0.1.1.dist-info/RECORD
