Metadata-Version: 2.1
Name: stream_downloader
Version: 0.1.1
Summary: Python library for downloading video streams by m3u8 file.
Author: ZnichkaDev
Project-URL: Homepage, https://github.com/ZnichkaDev/stream_downloader
Project-URL: Issues, https://github.com/ZnichkaDev/stream_downloader/issues
Project-URL: Repository, https://github.com/ZnichkaDev/stream_downloader.git
Classifier: Programming Language :: Python :: 3
Classifier: License :: OSI Approved :: MIT License
Classifier: Operating System :: OS Independent
Requires-Python: >=3.8
License-File: LICENSE
